pybenchatbot/__init__.py
pybenchatbot/__main__.py
pybenchatbot/botserver.py
pybenchatbot-1.1.0.dist-info/licenses/LICENSE
pybenchatbot-1.1.0.dist-info/METADATA
pybenchatbot-1.1.0.dist-info/WHEEL
pybenchatbot-1.1.0.dist-info/top_level.txt
pybenchatbot-1.1.0.dist-info/RECORD
