Metadata-Version: 2.4
Name: PyBenChatBot
Version: 1.1.0
Summary: PyBEN ChatBot enables anyone to run a custom chatbot on its own python module
Author: Ben Moskovitch
Author-email: Ben Moskovitch <darkflameben@gmail.com>
Maintainer-email: Ben Moskovitch <darkflameben@gmail.com>
License-Expression: MIT
Project-URL: Homepage, https://github.com/DarkFlameBEN/PyBenChatBot
Keywords: python,Chatbot,utils,utilities,automation,automation-tools
Classifier: Development Status :: 5 - Production/Stable
Classifier: Intended Audience :: Developers
Classifier: Topic :: Software Development :: Libraries
Classifier: Operating System :: OS Independent
Classifier: Programming Language :: Python :: 3.9
Classifier: Programming Language :: Python :: 3.10
Classifier: Programming Language :: Python :: 3.11
Classifier: Programming Language :: Python :: 3.12
Classifier: Programming Language :: Python :: 3.13
Requires-Python: >=3.9
License-File: LICENSE
Requires-Dist: fastapi
Requires-Dist: chromadb
Requires-Dist: uvicorn
Requires-Dist: sentence_transformers
Dynamic: license-file
